{
  "package": "@geoalgeria/ooredoo",
  "schema_version": "2.0.0",
  "title_fr": "Boutiques Ooredoo",
  "title_ar": "متاجر أوريدو",
  "title_en": "Ooredoo stores (Algeria)",
  "record_count": 572,
  "geocoded_count": 572,
  "geocoded_pct": 100,
  "precision": {
    "exact": 572,
    "approximate": 0
  },
  "estimated_universe": null,
  "coverage_pct": null,
  "coverage_note": "Ooredoo retail network (Espaces Ooredoo, City Shops, Espaces Services) via the public API — every record has a real operator coordinate. A few points carry inaccurate source coords, so their derived wilaya/commune may be off; operator_wilaya preserves the operator's declared wilaya.",
  "wilayas_covered": 63,
  "bbox": [
    -8.14028,
    22.7856,
    9.48333,
    37.0069
  ],
  "sources": [
    {
      "key": "ooredoo",
      "name": "Ooredoo Algérie — retail network (trouvez-nous JSON API)",
      "url": "https://www.ooredoo.dz/fr/particuliers/trouvez-nous",
      "license": "Data © Ooredoo Algérie; redistributed for reference",
      "retrieved": "2026-07-18",
      "evidence_type": "official"
    }
  ],
  "license": "Data © Ooredoo Algérie; redistributed for reference",
  "updated": "2026-07-18",
  "by_type": {
    "ESO": 436,
    "EO": 100,
    "CSO": 36
  }
}
