[
 {
  "layer": "cultural-directorate",
  "type_class": "various small embassy",
  "lat": 33.808965,
  "lng": 2.853571,
  "wilaya_slug": "03-laghouat",
  "name_fr": "Direction de la culture Laghouat",
  "name_ar": "مديرية الثقافة لولاية الأغواط",
  "nid_fr": "792",
  "nid_ar": "371"
 },
 {
  "layer": "cultural-directorate",
  "type_class": "various small embassy",
  "lat": 35.872919,
  "lng": 7.090653,
  "wilaya_slug": "04-oum-el-bouaghi",
  "name_fr": "Direction de la culture Oum el bouaghi",
  "name_ar": "مديرية الثقافة لولاية أم البواقي",
  "nid_fr": "588",
  "nid_ar": "589"
 },
 {
  "layer": "cultural-center",
  "type_class": "various small home",
  "lat": 36.041472,
  "lng": 6.562639,
  "wilaya_slug": "04-oum-el-bouaghi",
  "name_fr": "STATION AIN MLILA, CNRPAH",
  "name_ar": null,
  "nid_fr": "773",
  "nid_ar": null
 },
 {
  "layer": "cultural-directorate",
  "type_class": "various small embassy",
  "lat": 35.554543,
  "lng": 6.159407,
  "wilaya_slug": "05-batna",
  "name_fr": "Direction de la culture de Batna",
  "name_ar": "مديرية الثقافة باتنة",
  "nid_fr": "793",
  "nid_ar": "444"
 },
 {
  "layer": "cinema",
  "type_class": "various small video",
  "lat": 36.460437,
  "lng": 5.274001,
  "wilaya_slug": "06-béjaïa",
  "name_fr": "Salle de cimema 08 mai 1945",
  "name_ar": null,
  "nid_fr": "636",
  "nid_ar": null
 },
 {
  "layer": "cultural-directorate",
  "type_class": "various small embassy",
  "lat": 36.741141,
  "lng": 5.054028,
  "wilaya_slug": "06-béjaïa",
  "name_fr": "Direction de la culture de la wilaya de Bejaia",
  "name_ar": "مديرية الثقافة لولاية بجاية",
  "nid_fr": "637",
  "nid_ar": "740"
 },
 {
  "layer": "cultural-directorate",
  "type_class": "various small embassy",
  "lat": 34.85206,
  "lng": 5.73062,
  "wilaya_slug": "07-biskra",
  "name_fr": "Direction de la culture de Biskra",
  "name_ar": "مديرية الثقافة بسكرة",
  "nid_fr": "790",
  "nid_ar": "736"
 },
 {
  "layer": "cultural-directorate",
  "type_class": "various small embassy",
  "lat": 36.492605,
  "lng": 2.847731,
  "wilaya_slug": "09-blida",
  "name_fr": "Direction de la culture de Blida",
  "name_ar": "مديرية الثقافة لولاية البليدة",
  "nid_fr": "795",
  "nid_ar": "276"
 },
 {
  "layer": "cultural-house",
  "type_class": "various small house",
  "lat": 36.37407,
  "lng": 3.890497,
  "wilaya_slug": "10-bouira",
  "name_fr": "Maison de la Culture",
  "name_ar": "دار الثقافة \"علي زعموم \"",
  "nid_fr": "1304",
  "nid_ar": "1303"
 },
 {
  "layer": "cultural-directorate",
  "type_class": "various small embassy",
  "lat": 22.793524,
  "lng": 5.538415,
  "wilaya_slug": "11-tamanrasset",
  "name_fr": "Direction de la culture de Tamanrasset",
  "name_ar": "مديرية الثقافة لولاية تامنغست",
  "nid_fr": "796",
  "nid_ar": "487"
 },
 {
  "layer": "cultural-directorate",
  "type_class": "various small embassy",
  "lat": 35.399226,
  "lng": 8.112022,
  "wilaya_slug": "12-tébessa",
  "name_fr": "Direction de la culture de Tébessa",
  "name_ar": "مديرية الثقافة لولاية تبسة",
  "nid_fr": "797",
  "nid_ar": "594"
 },
 {
  "layer": "cultural-palace",
  "type_class": "various small palace-2",
  "lat": 34.916114,
  "lng": -1.35183,
  "wilaya_slug": "13-tlemcen",
  "name_fr": "Centre des Arts et des Expositions CAREX Tlemcen",
  "name_ar": null,
  "nid_fr": "218",
  "nid_ar": null
 },
 {
  "layer": "cultural-palace",
  "type_class": "various small palace-2",
  "lat": 34.879424,
  "lng": -1.335625,
  "wilaya_slug": "13-tlemcen",
  "name_fr": "Palais de la Culture Abdelkrim Dali",
  "name_ar": "قصر الثقافة عبد الكريم دالي",
  "nid_fr": "98",
  "nid_ar": "359"
 },
 {
  "layer": "cultural-center",
  "type_class": "various small home",
  "lat": 34.881044,
  "lng": -1.334187,
  "wilaya_slug": "13-tlemcen",
  "name_fr": "Centre des études andalouses, Station CNRPAH",
  "name_ar": null,
  "nid_fr": "771",
  "nid_ar": null
 },
 {
  "layer": "cultural-palace",
  "type_class": "various small palace-2",
  "lat": 34.879854,
  "lng": -1.334232,
  "wilaya_slug": "13-tlemcen",
  "name_fr": "Centre des Etudes et Recherches Andalouses",
  "name_ar": null,
  "nid_fr": "113",
  "nid_ar": null
 },
 {
  "layer": "cultural-center",
  "type_class": "various small home",
  "lat": 35.350991,
  "lng": 1.309988,
  "wilaya_slug": "14-tiaret",
  "name_fr": "Centre des études khaldouniennes",
  "name_ar": null,
  "nid_fr": "772",
  "nid_ar": null
 },
 {
  "layer": "cultural-directorate",
  "type_class": "various small embassy",
  "lat": 35.351395,
  "lng": 1.324281,
  "wilaya_slug": "14-tiaret",
  "name_fr": "Direction de la culture de Tiaret",
  "name_ar": "مديرية الثقافة ولاية تيارت",
  "nid_fr": "798",
  "nid_ar": "691"
 },
 {
  "layer": "cultural-directorate",
  "type_class": "various small embassy",
  "lat": 36.712944,
  "lng": 4.053722,
  "wilaya_slug": "15-tizi-ouzou",
  "name_fr": "Direction de la Culture de la wilaya de Tizi-Ouzou",
  "name_ar": "مديرية الثقافة تيزي وزو",
  "nid_fr": "229",
  "nid_ar": "316"
 },
 {
  "layer": "cultural-house",
  "type_class": "various small house",
  "lat": 36.713297,
  "lng": 4.053064,
  "wilaya_slug": "15-tizi-ouzou",
  "name_fr": "Maison de la Culture \"Mouloud MAMMERI\" de Tizi-Ouzou",
  "name_ar": null,
  "nid_fr": "349",
  "nid_ar": null
 },
 {
  "layer": "arts-school",
  "type_class": "various small school",
  "lat": 36.761822,
  "lng": 3.043774,
  "wilaya_slug": "16-alger",
  "name_fr": "École supérieure des beaux-arts d'Alger",
  "name_ar": null,
  "nid_fr": "780",
  "nid_ar": null
 },
 {
  "layer": "cultural-center",
  "type_class": "various small home",
  "lat": 36.77603,
  "lng": 3.054396,
  "wilaya_slug": "16-alger",
  "name_fr": "Centre National du Cinéma et de l’Audiovisuel (CNCA)",
  "name_ar": null,
  "nid_fr": "813",
  "nid_ar": null
 },
 {
  "layer": "cultural-center",
  "type_class": "various small home",
  "lat": 36.7883,
  "lng": 3.063994,
  "wilaya_slug": "16-alger",
  "name_fr": "Centre des Arts et de la Culture « PALAIS DES RAÏS »",
  "name_ar": null,
  "nid_fr": "123",
  "nid_ar": null
 },
 {
  "layer": "cultural-center",
  "type_class": "various small home",
  "lat": 36.774603,
  "lng": 3.058865,
  "wilaya_slug": "16-alger",
  "name_fr": "Centre Algérien de la Cinématographie (Cinémathèque)",
  "name_ar": null,
  "nid_fr": "471",
  "nid_ar": null
 },
 {
  "layer": "cinema",
  "type_class": "various small video",
  "lat": 36.791294,
  "lng": 3.059312,
  "wilaya_slug": "16-alger",
  "name_fr": "SALLE ATLAS",
  "name_ar": "قاعة الأطلس بباب الوادي",
  "nid_fr": "1428",
  "nid_ar": "1345"
 },
 {
  "layer": "cultural-center",
  "type_class": "various small home",
  "lat": 36.76467,
  "lng": 3.04532,
  "wilaya_slug": "16-alger",
  "name_fr": "Centre National de Recherche en Archéologie",
  "name_ar": "المركز الوطني للبحث في علم الآثار",
  "nid_fr": "812",
  "nid_ar": "1298"
 },
 {
  "layer": "cinema",
  "type_class": "various small video",
  "lat": 36.765059,
  "lng": 3.053089,
  "wilaya_slug": "16-alger",
  "name_fr": "Salle Afrique",
  "name_ar": null,
  "nid_fr": "1546",
  "nid_ar": null
 },
 {
  "layer": "cultural-house",
  "type_class": "various small house",
  "lat": 36.763056,
  "lng": 3.046667,
  "wilaya_slug": "16-alger",
  "name_fr": "Office National des Droits d'Auteurs et Droits Voisins",
  "name_ar": null,
  "nid_fr": "454",
  "nid_ar": null
 },
 {
  "layer": "cultural-palace",
  "type_class": "various small palace-2",
  "lat": 36.737999,
  "lng": 3.082556,
  "wilaya_slug": "16-alger",
  "name_fr": "Palais de la culture Moufdi Zakaria",
  "name_ar": "قصر الثقافة مفدي زكريا",
  "nid_fr": "67",
  "nid_ar": "548"
 },
 {
  "layer": "cultural-center",
  "type_class": "various small homecenter",
  "lat": 36.689317,
  "lng": 2.827552,
  "wilaya_slug": "16-alger",
  "name_fr": "Village des Artistes",
  "name_ar": null,
  "nid_fr": "1548",
  "nid_ar": null
 },
 {
  "layer": "cinema",
  "type_class": "various small video",
  "lat": 36.763679,
  "lng": 3.050721,
  "wilaya_slug": "16-alger",
  "name_fr": "Salle Sierra Maestra",
  "name_ar": null,
  "nid_fr": "1544",
  "nid_ar": null
 },
 {
  "layer": "cultural-directorate",
  "type_class": "various small embassy",
  "lat": 36.804306,
  "lng": 5.78675,
  "wilaya_slug": "18-jijel",
  "name_fr": "Direction de culture de la Wilaya de Jijel",
  "name_ar": "مديرية الثقافة لولاية جيجل",
  "nid_fr": "650",
  "nid_ar": "785"
 },
 {
  "layer": "arts-school",
  "type_class": "various small presentation",
  "lat": 36.206308,
  "lng": 5.449067,
  "wilaya_slug": "19-sétif",
  "name_fr": "L'Ecole Régionale des Beaux-Arts / Annexe Setif",
  "name_ar": "المدرسة االجهوية للفنون الجميلة ملحقة سطيف",
  "nid_fr": "1445",
  "nid_ar": "842"
 },
 {
  "layer": "cultural-directorate",
  "type_class": "various small embassy",
  "lat": 36.209366,
  "lng": 5.447655,
  "wilaya_slug": "19-sétif",
  "name_fr": "Direction de la culture et des arts",
  "name_ar": "مديرية الثقافة والفنون",
  "nid_fr": "1426",
  "nid_ar": "1138"
 },
 {
  "layer": "cultural-directorate",
  "type_class": "various small embassy",
  "lat": 34.827158,
  "lng": 0.156777,
  "wilaya_slug": "20-saïda",
  "name_fr": "Direction de la culture de Saïda",
  "name_ar": "مديرية الثقافة لولاية سعيدة",
  "nid_fr": "799",
  "nid_ar": "676"
 },
 {
  "layer": "cultural-directorate",
  "type_class": "various small embassy",
  "lat": 36.862833,
  "lng": 6.900583,
  "wilaya_slug": "21-skikda",
  "name_fr": "Direction de la culture de Skikda",
  "name_ar": "مديرية الثقافة لولاية سكيكدة",
  "nid_fr": "741",
  "nid_ar": "688"
 },
 {
  "layer": "cultural-directorate",
  "type_class": "various small embassy",
  "lat": 35.728621,
  "lng": 4.51511,
  "wilaya_slug": "28-msila",
  "name_fr": "Direction de la culture de la wilaya de M'sila",
  "name_ar": "مديرية الثقافة لولاية المسيلة",
  "nid_fr": "802",
  "nid_ar": "598"
 },
 {
  "layer": "cinema",
  "type_class": "various small video",
  "lat": 35.704231,
  "lng": 4.544379,
  "wilaya_slug": "28-msila",
  "name_fr": "salle de cinéma El-Hodna",
  "name_ar": "قاعة سينما الحضنة",
  "nid_fr": "1551",
  "nid_ar": "1123"
 },
 {
  "layer": "cultural-center",
  "type_class": "various small home",
  "lat": 35.236407,
  "lng": 4.162894,
  "wilaya_slug": "28-msila",
  "name_fr": "02.\tAnnexe du centre national de recherches préhistoriques, anthropologiques et historiques.",
  "name_ar": "CNRPAH ملحقة المركز الوطني للبحوث في عصور ما قبل التاريخ وفى علم الإنسان والتاريخ",
  "nid_fr": "1550",
  "nid_ar": "1122"
 },
 {
  "layer": "cultural-directorate",
  "type_class": "various small embassy",
  "lat": 35.406373,
  "lng": 0.143452,
  "wilaya_slug": "29-mascara",
  "name_fr": "Direction de la culture de Mascara",
  "name_ar": "مديرية الثقافة لولاية معسكر",
  "nid_fr": "788",
  "nid_ar": "784"
 },
 {
  "layer": "cultural-directorate",
  "type_class": "various small embassy",
  "lat": 31.934801,
  "lng": 5.30434,
  "wilaya_slug": "30-ouargla",
  "name_fr": "Direction de la culture de Ouargla",
  "name_ar": "مديرية الثقافة لولاية ورقلة",
  "nid_fr": "626",
  "nid_ar": "641"
 },
 {
  "layer": "cultural-directorate",
  "type_class": "various small embassy",
  "lat": 36.768656,
  "lng": 8.309898,
  "wilaya_slug": "36-el-tarf",
  "name_fr": "Direction de la culture de El Tarf",
  "name_ar": "مديرية الثقافة لولاية الطارف",
  "nid_fr": "803",
  "nid_ar": "662"
 },
 {
  "layer": "cultural-directorate",
  "type_class": "various small embassy",
  "lat": 27.653732,
  "lng": -8.124937,
  "wilaya_slug": "37-tindouf",
  "name_fr": "direction de la culture Tindouf",
  "name_ar": "مديرية الثقافة",
  "nid_fr": "1557",
  "nid_ar": "1099"
 },
 {
  "layer": "cultural-directorate",
  "type_class": "various small embassy",
  "lat": 35.599153,
  "lng": 1.809182,
  "wilaya_slug": "38-tissemsilt",
  "name_fr": "Direction de la culture de Tissemsilt",
  "name_ar": "مديرية الثقافة لولاية تيسمسيلت",
  "nid_fr": "804",
  "nid_ar": "686"
 },
 {
  "layer": "cultural-house",
  "type_class": "various small house",
  "lat": 33.35983,
  "lng": 6.865004,
  "wilaya_slug": "39-el-oued",
  "name_fr": "Maisons de culture El Oued",
  "name_ar": "دار الثقافة محمد الأمين العمودي",
  "nid_fr": "70",
  "nid_ar": "713"
 },
 {
  "layer": "cultural-directorate",
  "type_class": "various small embassy",
  "lat": 33.397561,
  "lng": 6.871544,
  "wilaya_slug": "39-el-oued",
  "name_fr": "Direction de la culture de El Oued",
  "name_ar": "مديرية الثقافة الوادي",
  "nid_fr": "805",
  "nid_ar": "608"
 },
 {
  "layer": "cultural-house",
  "type_class": "various small house",
  "lat": 35.435807,
  "lng": 7.138031,
  "wilaya_slug": "40-khenchela",
  "name_fr": "OGEBC KHENCHELA",
  "name_ar": "فرع الديوان الوطني لتسيير و استغلال الممتلكات الثقافية المحمية خنشلة",
  "nid_fr": "1552",
  "nid_ar": "850"
 },
 {
  "layer": "cinema",
  "type_class": "various small video",
  "lat": 35.426678,
  "lng": 7.146707,
  "wilaya_slug": "40-khenchela",
  "name_fr": "cinématographique (khenchela)",
  "name_ar": "سينماتيك خنشلة",
  "nid_fr": "1337",
  "nid_ar": "853"
 },
 {
  "layer": "cultural-directorate",
  "type_class": "various small embassy",
  "lat": 35.435756,
  "lng": 7.138009,
  "wilaya_slug": "40-khenchela",
  "name_fr": "Direction de la culture de Khenchela",
  "name_ar": "مديرية الثقافة لولاية خنشلة",
  "nid_fr": "806",
  "nid_ar": "536"
 },
 {
  "layer": "cultural-directorate",
  "type_class": "various small embassy",
  "lat": 36.280381,
  "lng": 7.935725,
  "wilaya_slug": "41-souk-ahras",
  "name_fr": "Direction de la culture et des arts de Souk Ahras",
  "name_ar": "مديرية الثقافة و الفنون لولاية سوق أهراس سوق اهراس ( مؤسسة منجزة حيز الخدمة))",
  "nid_fr": "807",
  "nid_ar": "227"
 },
 {
  "layer": "cultural-house",
  "type_class": "various small house",
  "lat": 36.280451,
  "lng": 7.936024,
  "wilaya_slug": "41-souk-ahras",
  "name_fr": "Maison de la CultureTahar Ouattar",
  "name_ar": "دار الثقافة الطاهر وطار سوق أهراس",
  "nid_fr": "1363",
  "nid_ar": "858"
 },
 {
  "layer": "cinema",
  "type_class": "various small video",
  "lat": 36.284174,
  "lng": 7.954642,
  "wilaya_slug": "41-souk-ahras",
  "name_fr": "cinémathèque Souk Ahras",
  "name_ar": "متحف السينما سوق اهراس",
  "nid_fr": "1380",
  "nid_ar": "210"
 },
 {
  "layer": "cultural-directorate",
  "type_class": "various small embassy",
  "lat": 36.592638,
  "lng": 2.450734,
  "wilaya_slug": "42-tipaza",
  "name_fr": "direction de la culture et des arts de la wilaya  de tipasa",
  "name_ar": "مديرية الثقافة  والفنون ولاية تيبازة",
  "nid_fr": "1421",
  "nid_ar": "1352"
 },
 {
  "layer": "arts-school",
  "type_class": "various small school",
  "lat": 36.589928,
  "lng": 2.453212,
  "wilaya_slug": "42-tipaza",
  "name_fr": "Ecole Régionale des Beaux –Arts  de la Wilaya de Tipasa.",
  "name_ar": "المدرسة الجهوية للفنون الجميلة ولاية تيبازة",
  "nid_fr": "1528",
  "nid_ar": "843"
 },
 {
  "layer": "cultural-center",
  "type_class": "various small home",
  "lat": 36.591684,
  "lng": 2.459237,
  "wilaya_slug": "42-tipaza",
  "name_fr": "Centre arabe d'archéologie",
  "name_ar": null,
  "nid_fr": "18",
  "nid_ar": null
 },
 {
  "layer": "cultural-house",
  "type_class": "various small house",
  "lat": 36.605687,
  "lng": 2.407727,
  "wilaya_slug": "42-tipaza",
  "name_fr": "Complexe Culturel de l'artiste  \"Abdelwahab Salim\" du Chenoua",
  "name_ar": "المركب الثقافي \" عبد الوهاب سليم \" بشنوة  تيبازة",
  "nid_fr": "1008",
  "nid_ar": "1007"
 },
 {
  "layer": "cultural-center",
  "type_class": "various small home",
  "lat": 36.442071,
  "lng": 6.258075,
  "wilaya_slug": "43-mila",
  "name_fr": "Maison de la Culture Moubarak El-Mili",
  "name_ar": "دار الثقافة مبارك الميلي",
  "nid_fr": "1554",
  "nid_ar": "496"
 },
 {
  "layer": "cultural-directorate",
  "type_class": "various small embassy",
  "lat": 36.262997,
  "lng": 1.954141,
  "wilaya_slug": "44-aïn-defla",
  "name_fr": "Direction de la culture de Aïn Defla",
  "name_ar": "مديرية الثقافة عين الدفلى",
  "nid_fr": "808",
  "nid_ar": "505"
 },
 {
  "layer": "cultural-directorate",
  "type_class": "various small embassy",
  "lat": 33.281,
  "lng": -0.309861,
  "wilaya_slug": "45-naâma",
  "name_fr": "Direction de la culture de Naâma",
  "name_ar": "مديرية الثقافة لولاية النعامة",
  "nid_fr": "809",
  "nid_ar": "679"
 },
 {
  "layer": "cinema",
  "type_class": "various small video",
  "lat": 35.290961,
  "lng": -1.141322,
  "wilaya_slug": "46-aïn-témouchent",
  "name_fr": "salle cinéma FLAOUCEN",
  "name_ar": "قاعة السينيما فلاوسن",
  "nid_fr": "1461",
  "nid_ar": "840"
 },
 {
  "layer": "cinema",
  "type_class": "various small video",
  "lat": 35.292874,
  "lng": -1.140882,
  "wilaya_slug": "46-aïn-témouchent",
  "name_fr": "salle de cinéma soummam",
  "name_ar": "قاعة السنيما الصومام",
  "nid_fr": "1466",
  "nid_ar": "839"
 },
 {
  "layer": "cultural-directorate",
  "type_class": "various small embassy",
  "lat": 35.304899,
  "lng": -1.143933,
  "wilaya_slug": "46-aïn-témouchent",
  "name_fr": "Direction de la culture",
  "name_ar": "مديرية الثقافة",
  "nid_fr": "1454",
  "nid_ar": "1227"
 },
 {
  "layer": "cultural-house",
  "type_class": "various small house",
  "lat": 27.868941,
  "lng": -0.295321,
  "wilaya_slug": "01-adrar",
  "name_fr": null,
  "name_ar": "الديوان الوطني للحظيرة الثقافية  لتوات قورارة تيديكلت",
  "nid_fr": null,
  "nid_ar": "882"
 },
 {
  "layer": "cultural-center",
  "type_class": "various small home",
  "lat": 27.886836,
  "lng": -0.286745,
  "wilaya_slug": "01-adrar",
  "name_fr": null,
  "name_ar": "المركز الوطني للمخطوطات",
  "nid_fr": null,
  "nid_ar": "643"
 },
 {
  "layer": "cultural-house",
  "type_class": "various small house",
  "lat": 27.873212,
  "lng": -0.289687,
  "wilaya_slug": "01-adrar",
  "name_fr": null,
  "name_ar": "دار الثقافة الشهيدي شيباني محمد أدرار",
  "nid_fr": null,
  "nid_ar": "633"
 },
 {
  "layer": "cultural-palace",
  "type_class": "various small palace-2",
  "lat": 27.878288,
  "lng": -0.263559,
  "wilaya_slug": "01-adrar",
  "name_fr": null,
  "name_ar": "قصر الثقافة الفنون",
  "nid_fr": null,
  "nid_ar": "885"
 },
 {
  "layer": "cultural-house",
  "type_class": "various small house",
  "lat": 36.161663,
  "lng": 1.344937,
  "wilaya_slug": "02-chlef",
  "name_fr": null,
  "name_ar": "دار الثقافة",
  "nid_fr": null,
  "nid_ar": "976"
 },
 {
  "layer": "arts-school",
  "type_class": "various small presentation",
  "lat": 36.1664,
  "lng": 1.337966,
  "wilaya_slug": "02-chlef",
  "name_fr": null,
  "name_ar": "معهد الموسيقى الهاشمي قروابي",
  "nid_fr": null,
  "nid_ar": "1029"
 },
 {
  "layer": "cinema",
  "type_class": "various small video",
  "lat": 36.510365,
  "lng": 1.306264,
  "wilaya_slug": "02-chlef",
  "name_fr": null,
  "name_ar": "قاعة سينما الجديدة –تنس",
  "nid_fr": null,
  "nid_ar": "1030"
 },
 {
  "layer": "cultural-house",
  "type_class": "various small house",
  "lat": 33.793336,
  "lng": 2.860995,
  "wilaya_slug": "03-laghouat",
  "name_fr": null,
  "name_ar": "دار الثقافة \"التخي عبد الله بن كريو\"",
  "nid_fr": null,
  "nid_ar": "368"
 },
 {
  "layer": "cinema",
  "type_class": "various small video",
  "lat": 34.113452,
  "lng": 2.101882,
  "wilaya_slug": "03-laghouat",
  "name_fr": null,
  "name_ar": "قاعة سينما سيدي عقبة",
  "nid_fr": null,
  "nid_ar": "306"
 },
 {
  "layer": "cultural-house",
  "type_class": "various small house",
  "lat": 34.105951,
  "lng": 2.075336,
  "wilaya_slug": "03-laghouat",
  "name_fr": null,
  "name_ar": "المركز الثقافي \"الشهيد أحمد فراحتية\"",
  "nid_fr": null,
  "nid_ar": "366"
 },
 {
  "layer": "cultural-house",
  "type_class": "various small house",
  "lat": 35.869333,
  "lng": 7.115389,
  "wilaya_slug": "04-oum-el-bouaghi",
  "name_fr": null,
  "name_ar": "دار الثقافة نوار بوبكر",
  "nid_fr": null,
  "nid_ar": "642"
 },
 {
  "layer": "arts-school",
  "type_class": "various small presentation",
  "lat": 35.549376,
  "lng": 6.168721,
  "wilaya_slug": "05-batna",
  "name_fr": null,
  "name_ar": "المعهد الجهوي للتكوين الموسيقي باتنة",
  "nid_fr": null,
  "nid_ar": "312"
 },
 {
  "layer": "cultural-center",
  "type_class": "various small home",
  "lat": 35.494775,
  "lng": 6.247816,
  "wilaya_slug": "05-batna",
  "name_fr": null,
  "name_ar": "المركز الوطني للبحث في علم الأثار –ملحقة تازولت- باتنة-",
  "nid_fr": null,
  "nid_ar": "465"
 },
 {
  "layer": "cultural-house",
  "type_class": "various small house",
  "lat": 35.62648,
  "lng": 6.264811,
  "wilaya_slug": "05-batna",
  "name_fr": null,
  "name_ar": "المركز الثقافي فيسديس",
  "nid_fr": null,
  "nid_ar": "457"
 },
 {
  "layer": "cultural-house",
  "type_class": "various small house",
  "lat": 35.553712,
  "lng": 6.181606,
  "wilaya_slug": "05-batna",
  "name_fr": null,
  "name_ar": "دار الثقافة محمد العيد آل خليفة",
  "nid_fr": null,
  "nid_ar": "238"
 },
 {
  "layer": "arts-school",
  "type_class": "various small presentation",
  "lat": 35.553667,
  "lng": 6.157972,
  "wilaya_slug": "05-batna",
  "name_fr": null,
  "name_ar": "المدرسة الجهوية للفنون الجميلة",
  "nid_fr": null,
  "nid_ar": "434"
 },
 {
  "layer": "arts-school",
  "type_class": "various small presentation",
  "lat": 34.846889,
  "lng": 5.700476,
  "wilaya_slug": "07-biskra",
  "name_fr": null,
  "name_ar": "ملحق المدرسة الجهوية للفون الجميلة",
  "nid_fr": null,
  "nid_ar": "739"
 },
 {
  "layer": "cultural-house",
  "type_class": "various small house",
  "lat": 34.852047,
  "lng": 5.730145,
  "wilaya_slug": "07-biskra",
  "name_fr": null,
  "name_ar": "دار الثقافة احمد رضا حوحو",
  "nid_fr": null,
  "nid_ar": "582"
 },
 {
  "layer": "cultural-center",
  "type_class": "various small home",
  "lat": 34.847289,
  "lng": 5.699688,
  "wilaya_slug": "07-biskra",
  "name_fr": null,
  "name_ar": "ملحقة المركز الوطني للمخطوطات",
  "nid_fr": null,
  "nid_ar": "738"
 },
 {
  "layer": "arts-school",
  "type_class": "various small presentation",
  "lat": 34.847395,
  "lng": 5.700554,
  "wilaya_slug": "07-biskra",
  "name_fr": null,
  "name_ar": "ملحق المعهد الجهوي للتكوين الموسيقي",
  "nid_fr": null,
  "nid_ar": "737"
 },
 {
  "layer": "cinema",
  "type_class": "various small video",
  "lat": 31.618164,
  "lng": -2.215949,
  "wilaya_slug": "08-bechar",
  "name_fr": null,
  "name_ar": "متحف السينما",
  "nid_fr": null,
  "nid_ar": "624"
 },
 {
  "layer": "cultural-directorate",
  "type_class": "various small embassy",
  "lat": 36.369185,
  "lng": 3.900619,
  "wilaya_slug": "10-bouira",
  "name_fr": null,
  "name_ar": "مقر مديرية الثقافة لولاية البويرة",
  "nid_fr": null,
  "nid_ar": "1100"
 },
 {
  "layer": "cultural-house",
  "type_class": "various small house",
  "lat": 22.78793,
  "lng": 5.525793,
  "wilaya_slug": "11-tamanrasset",
  "name_fr": null,
  "name_ar": "دار الثقافة تامنغست",
  "nid_fr": null,
  "nid_ar": "302"
 },
 {
  "layer": "cultural-house",
  "type_class": "various small house",
  "lat": 35.39952,
  "lng": 8.111921,
  "wilaya_slug": "12-tébessa",
  "name_fr": null,
  "name_ar": "دار الثقافــة لولايــة تبســة",
  "nid_fr": null,
  "nid_ar": "241"
 },
 {
  "layer": "cultural-center",
  "type_class": "various small home",
  "lat": 34.91156,
  "lng": 1.339969,
  "wilaya_slug": "13-tlemcen",
  "name_fr": null,
  "name_ar": "مركز الفنون و المعارض تلمسان",
  "nid_fr": null,
  "nid_ar": "1019"
 },
 {
  "layer": "arts-school",
  "type_class": "various small presentation",
  "lat": 35.3495,
  "lng": 1.3132,
  "wilaya_slug": "14-tiaret",
  "name_fr": null,
  "name_ar": "ملحقة الفنون الجميلة",
  "nid_fr": null,
  "nid_ar": "1174"
 },
 {
  "layer": "cultural-house",
  "type_class": "various small house",
  "lat": 36.770408,
  "lng": 3.054952,
  "wilaya_slug": "16-alger",
  "name_fr": null,
  "name_ar": "الديوان الوطني للثقافة والإعلام",
  "nid_fr": null,
  "nid_ar": "1343"
 },
 {
  "layer": "cinema",
  "type_class": "various small video",
  "lat": 34.830194,
  "lng": 0.152521,
  "wilaya_slug": "20-saïda",
  "name_fr": null,
  "name_ar": "Salle de Cinéma Dounia Zed",
  "nid_fr": null,
  "nid_ar": "244"
 },
 {
  "layer": "cultural-house",
  "type_class": "various small house",
  "lat": 36.868054,
  "lng": 6.909407,
  "wilaya_slug": "21-skikda",
  "name_fr": null,
  "name_ar": "دار الثقافة محمد سراج",
  "nid_fr": null,
  "nid_ar": "705"
 },
 {
  "layer": "cultural-palace",
  "type_class": "various small palace-2",
  "lat": 36.882194,
  "lng": 6.911139,
  "wilaya_slug": "21-skikda",
  "name_fr": null,
  "name_ar": "قصر الثقافة لسكيكدة مالك شبل",
  "nid_fr": null,
  "nid_ar": "730"
 },
 {
  "layer": "cinema",
  "type_class": "various small video",
  "lat": 35.188161,
  "lng": -0.633053,
  "wilaya_slug": "22-sidi-bel-abbès",
  "name_fr": null,
  "name_ar": "قاعة سينما العمارنة",
  "nid_fr": null,
  "nid_ar": "697"
 },
 {
  "layer": "cinema",
  "type_class": "various small video",
  "lat": 35.192784,
  "lng": -0.634117,
  "wilaya_slug": "22-sidi-bel-abbès",
  "name_fr": null,
  "name_ar": "قاعة سينما تسالة",
  "nid_fr": null,
  "nid_ar": "696"
 },
 {
  "layer": "cinema",
  "type_class": "various small video",
  "lat": 36.90659,
  "lng": 7.760337,
  "wilaya_slug": "23-annaba",
  "name_fr": null,
  "name_ar": "السينماتيك",
  "nid_fr": null,
  "nid_ar": "472"
 },
 {
  "layer": "arts-school",
  "type_class": "various small presentation",
  "lat": 36.861603,
  "lng": 7.738624,
  "wilaya_slug": "23-annaba",
  "name_fr": null,
  "name_ar": "مدرسة الفنون الجميلة - ملحقة عنابة",
  "nid_fr": null,
  "nid_ar": "975"
 },
 {
  "layer": "arts-school",
  "type_class": "various small presentation",
  "lat": 36.861574,
  "lng": 7.737701,
  "wilaya_slug": "23-annaba",
  "name_fr": null,
  "name_ar": "معهد التكوين الموسيقي",
  "nid_fr": null,
  "nid_ar": "974"
 },
 {
  "layer": "arts-school",
  "type_class": "various small presentation",
  "lat": 36.443789,
  "lng": 7.425367,
  "wilaya_slug": "24-guelma",
  "name_fr": null,
  "name_ar": "ملحقة مدرسة الفنون الجميلة",
  "nid_fr": null,
  "nid_ar": "1001"
 },
 {
  "layer": "cultural-house",
  "type_class": "various small house",
  "lat": 36.458833,
  "lng": 7.424083,
  "wilaya_slug": "24-guelma",
  "name_fr": null,
  "name_ar": "دار الثقافة قالمة",
  "nid_fr": null,
  "nid_ar": "670"
 },
 {
  "layer": "cultural-house",
  "type_class": "various small house",
  "lat": 36.351324,
  "lng": 6.606888,
  "wilaya_slug": "25-constantine",
  "name_fr": null,
  "name_ar": "دار الثقافة مالك حداد قسنطينة",
  "nid_fr": null,
  "nid_ar": "1415"
 },
 {
  "layer": "cultural-house",
  "type_class": "various small house",
  "lat": 36.260251,
  "lng": 2.761663,
  "wilaya_slug": "26-médéa",
  "name_fr": null,
  "name_ar": "دار الثقافة حسن الحسني لولاية المدية",
  "nid_fr": null,
  "nid_ar": "352"
 },
 {
  "layer": "arts-school",
  "type_class": "various small presentation",
  "lat": 35.926111,
  "lng": 0.079167,
  "wilaya_slug": "27-mostaganem",
  "name_fr": null,
  "name_ar": "معهد الموسيقى لولاية مستغانم",
  "nid_fr": null,
  "nid_ar": "211"
 },
 {
  "layer": "arts-school",
  "type_class": "various small presentation",
  "lat": 35.920836,
  "lng": 0.064546,
  "wilaya_slug": "27-mostaganem",
  "name_fr": null,
  "name_ar": "المدرسة الجهوية للفنون الجميلة \" محمد خدة \" مستغانم",
  "nid_fr": null,
  "nid_ar": "268"
 },
 {
  "layer": "cultural-house",
  "type_class": "various small house",
  "lat": 35.70675,
  "lng": 4.535444,
  "wilaya_slug": "28-msila",
  "name_fr": null,
  "name_ar": "دار الثقافة الشهيد  قنفود الحملاوي",
  "nid_fr": null,
  "nid_ar": "597"
 },
 {
  "layer": "cultural-house",
  "type_class": "various small house",
  "lat": 35.406078,
  "lng": 0.142913,
  "wilaya_slug": "29-mascara",
  "name_fr": null,
  "name_ar": "دار الثقافة أبي راس الناصري معسكر",
  "nid_fr": null,
  "nid_ar": "1055"
 },
 {
  "layer": "cultural-house",
  "type_class": "various small house",
  "lat": 31.959167,
  "lng": 5.329083,
  "wilaya_slug": "30-ouargla",
  "name_fr": null,
  "name_ar": "دار الثقافة مفدي زكريا",
  "nid_fr": null,
  "nid_ar": "838"
 },
 {
  "layer": "cultural-house",
  "type_class": "various small house",
  "lat": 31.958458,
  "lng": 5.328279,
  "wilaya_slug": "30-ouargla",
  "name_fr": null,
  "name_ar": "دار الثقافة ورقلة",
  "nid_fr": null,
  "nid_ar": "647"
 },
 {
  "layer": "cultural-directorate",
  "type_class": "various small embassy",
  "lat": 33.678648,
  "lng": 1.013394,
  "wilaya_slug": "32-el-bayadh",
  "name_fr": null,
  "name_ar": "مديرية الثقافة لولاية البيض",
  "nid_fr": null,
  "nid_ar": "1067"
 },
 {
  "layer": "cultural-house",
  "type_class": "various small house",
  "lat": 33.685083,
  "lng": 1.01075,
  "wilaya_slug": "32-el-bayadh",
  "name_fr": null,
  "name_ar": "دار الثقافة محمد بلخير",
  "nid_fr": null,
  "nid_ar": "296"
 },
 {
  "layer": "cultural-directorate",
  "type_class": "various small embassy",
  "lat": 26.502176,
  "lng": 8.483527,
  "wilaya_slug": "33-illizi",
  "name_fr": null,
  "name_ar": "مديرية الثقافة لولاية إليزي",
  "nid_fr": null,
  "nid_ar": "751"
 },
 {
  "layer": "cinema",
  "type_class": "various small video",
  "lat": 28.045982,
  "lng": 9.575973,
  "wilaya_slug": "33-illizi",
  "name_fr": null,
  "name_ar": "قاعة سينما - إن إمناس",
  "nid_fr": null,
  "nid_ar": "754"
 },
 {
  "layer": "cultural-house",
  "type_class": "various small house",
  "lat": 26.501052,
  "lng": 8.482313,
  "wilaya_slug": "33-illizi",
  "name_fr": null,
  "name_ar": "دار الثقافة عثماني بالي",
  "nid_fr": null,
  "nid_ar": "747"
 },
 {
  "layer": "cultural-house",
  "type_class": "various small house",
  "lat": 24.477542,
  "lng": 9.511575,
  "wilaya_slug": "33-illizi",
  "name_fr": null,
  "name_ar": "المركز الثقافي بإفري",
  "nid_fr": null,
  "nid_ar": "749"
 },
 {
  "layer": "cultural-house",
  "type_class": "various small house",
  "lat": 24.562992,
  "lng": 9.453884,
  "wilaya_slug": "33-illizi",
  "name_fr": null,
  "name_ar": "الديوان الوطني للحظيرة الثقافية للتاسيلي ن-آزجر",
  "nid_fr": null,
  "nid_ar": "966"
 },
 {
  "layer": "cultural-house",
  "type_class": "various small house",
  "lat": 36.073472,
  "lng": 4.749592,
  "wilaya_slug": "34-bordj-bou-arreridj",
  "name_fr": null,
  "name_ar": "دار الثقافة محمد بوضياف",
  "nid_fr": null,
  "nid_ar": "286"
 },
 {
  "layer": "cultural-house",
  "type_class": "various small house",
  "lat": 36.149723,
  "lng": 4.972222,
  "wilaya_slug": "34-bordj-bou-arreridj",
  "name_fr": null,
  "name_ar": "المركز الثقافي الشهيد يعقوبي عمار بلدية حسناوة",
  "nid_fr": null,
  "nid_ar": "704"
 },
 {
  "layer": "cultural-house",
  "type_class": "various small house",
  "lat": 35.976737,
  "lng": 4.879201,
  "wilaya_slug": "34-bordj-bou-arreridj",
  "name_fr": null,
  "name_ar": "ملحقة دار الثقافة لعروسي بورزق",
  "nid_fr": null,
  "nid_ar": "305"
 },
 {
  "layer": "cultural-house",
  "type_class": "various small house",
  "lat": 36.024471,
  "lng": 5.050767,
  "wilaya_slug": "34-bordj-bou-arreridj",
  "name_fr": null,
  "name_ar": "المركز الثقافي مكاري السعيد بلدية تكستار",
  "nid_fr": null,
  "nid_ar": "706"
 },
 {
  "layer": "cultural-house",
  "type_class": "various small house",
  "lat": 36.151112,
  "lng": 4.355,
  "wilaya_slug": "34-bordj-bou-arreridj",
  "name_fr": null,
  "name_ar": "المركز الثقافي المجاهد محمد منتاش بلدية حرازة",
  "nid_fr": null,
  "nid_ar": "702"
 },
 {
  "layer": "cultural-house",
  "type_class": "various small house",
  "lat": 36.074613,
  "lng": 4.754439,
  "wilaya_slug": "34-bordj-bou-arreridj",
  "name_fr": null,
  "name_ar": "المركب الثقافي عائشة حداد",
  "nid_fr": null,
  "nid_ar": "299"
 },
 {
  "layer": "cultural-directorate",
  "type_class": "various small embassy",
  "lat": 36.08938,
  "lng": 4.770377,
  "wilaya_slug": "34-bordj-bou-arreridj",
  "name_fr": null,
  "name_ar": "مديرية الثقافة لولاية برج بوعريريج",
  "nid_fr": null,
  "nid_ar": "899"
 },
 {
  "layer": "cultural-house",
  "type_class": "various small house",
  "lat": 36.294445,
  "lng": 4.668334,
  "wilaya_slug": "34-bordj-bou-arreridj",
  "name_fr": null,
  "name_ar": "المركز الثقافي بوشيحة مزيان بلدية جعافرة",
  "nid_fr": null,
  "nid_ar": "698"
 },
 {
  "layer": "cultural-house",
  "type_class": "various small house",
  "lat": 36.271946,
  "lng": 4.837222,
  "wilaya_slug": "34-bordj-bou-arreridj",
  "name_fr": null,
  "name_ar": "المركز الثقافي شيباني الصالح بلدية برج زمورة",
  "nid_fr": null,
  "nid_ar": "700"
 },
 {
  "layer": "cultural-house",
  "type_class": "various small house",
  "lat": 35.948055,
  "lng": 4.686389,
  "wilaya_slug": "34-bordj-bou-arreridj",
  "name_fr": null,
  "name_ar": "المركز الثقافي حريزي احمد بلدية العش",
  "nid_fr": null,
  "nid_ar": "707"
 },
 {
  "layer": "cultural-house",
  "type_class": "various small house",
  "lat": 36.178333,
  "lng": 5.027222,
  "wilaya_slug": "34-bordj-bou-arreridj",
  "name_fr": null,
  "name_ar": "المركز الثقافي بن علية عبد الله بلدية خليل",
  "nid_fr": null,
  "nid_ar": "701"
 },
 {
  "layer": "cultural-directorate",
  "type_class": "various small embassy",
  "lat": 36.761104,
  "lng": 3.474944,
  "wilaya_slug": "35-boumerdès",
  "name_fr": null,
  "name_ar": "مديرية الثقافة لولاية بومرداس",
  "nid_fr": null,
  "nid_ar": "1033"
 },
 {
  "layer": "cultural-house",
  "type_class": "various small house",
  "lat": 36.764894,
  "lng": 3.47655,
  "wilaya_slug": "35-boumerdès",
  "name_fr": null,
  "name_ar": "دار الثقافة رشيد ميموني بومرداس",
  "nid_fr": null,
  "nid_ar": "1034"
 },
 {
  "layer": "cultural-house",
  "type_class": "various small house",
  "lat": 28.614405,
  "lng": -6.979277,
  "wilaya_slug": "37-tindouf",
  "name_fr": null,
  "name_ar": "الديوان الوطني للحظيرة الثقافية لتندوف ، قسم أم العسل",
  "nid_fr": null,
  "nid_ar": "1107"
 },
 {
  "layer": "cultural-house",
  "type_class": "various small house",
  "lat": 27.671788,
  "lng": -8.13489,
  "wilaya_slug": "37-tindouf",
  "name_fr": null,
  "name_ar": "الديوان الوطني للحظيرة الثقافية لتندوف",
  "nid_fr": null,
  "nid_ar": "1106"
 },
 {
  "layer": "cultural-house",
  "type_class": "various small house",
  "lat": 35.604112,
  "lng": 1.808659,
  "wilaya_slug": "38-tissemsilt",
  "name_fr": null,
  "name_ar": "دار الثقافة لولاية تيسمسيلت",
  "nid_fr": null,
  "nid_ar": "693"
 },
 {
  "layer": "cultural-house",
  "type_class": "various small house",
  "lat": 33.396379,
  "lng": 6.871738,
  "wilaya_slug": "39-el-oued",
  "name_fr": null,
  "name_ar": "دار الثقافة لولاية الوادي",
  "nid_fr": null,
  "nid_ar": "272"
 },
 {
  "layer": "cultural-house",
  "type_class": "various small house",
  "lat": 35.429457,
  "lng": 7.149079,
  "wilaya_slug": "40-khenchela",
  "name_fr": null,
  "name_ar": "دار الثقافة علي سوايعي",
  "nid_fr": null,
  "nid_ar": "745"
 },
 {
  "layer": "arts-school",
  "type_class": "various small presentation",
  "lat": 36.589791,
  "lng": 2.453165,
  "wilaya_slug": "42-tipaza",
  "name_fr": null,
  "name_ar": "المدرسة الجهوية للفنون الجميلة بتيبازة",
  "nid_fr": null,
  "nid_ar": "574"
 },
 {
  "layer": "cultural-house",
  "type_class": "various small house",
  "lat": 36.64069,
  "lng": 2.764274,
  "wilaya_slug": "42-tipaza",
  "name_fr": null,
  "name_ar": "دار الثقافة احمد عروة لولاية تيبازة بالقليعة",
  "nid_fr": null,
  "nid_ar": "329"
 },
 {
  "layer": "cinema",
  "type_class": "various small video",
  "lat": 36.260099,
  "lng": 2.216905,
  "wilaya_slug": "44-aïn-defla",
  "name_fr": null,
  "name_ar": "سينما الكواكب",
  "nid_fr": null,
  "nid_ar": "878"
 },
 {
  "layer": "cultural-house",
  "type_class": "various small house",
  "lat": 32.757917,
  "lng": -0.584778,
  "wilaya_slug": "45-naâma",
  "name_fr": null,
  "name_ar": "ملحقة دار الثقافة بلقاسم بغدادي",
  "nid_fr": null,
  "nid_ar": "627"
 },
 {
  "layer": "cinema",
  "type_class": "various small video",
  "lat": 33.547917,
  "lng": -0.278167,
  "wilaya_slug": "45-naâma",
  "name_fr": null,
  "name_ar": "قاعة سينما الامل",
  "nid_fr": null,
  "nid_ar": "573"
 },
 {
  "layer": "cinema",
  "type_class": "various small video",
  "lat": 32.754306,
  "lng": -0.58425,
  "wilaya_slug": "45-naâma",
  "name_fr": null,
  "name_ar": "قاعة سينما أمزي",
  "nid_fr": null,
  "nid_ar": "575"
 },
 {
  "layer": "cultural-house",
  "type_class": "various small house",
  "lat": 33.277677,
  "lng": -0.309377,
  "wilaya_slug": "45-naâma",
  "name_fr": null,
  "name_ar": "دار الثقافة أحمد شامي",
  "nid_fr": null,
  "nid_ar": "456"
 },
 {
  "layer": "cultural-house",
  "type_class": "various small house",
  "lat": 35.304866,
  "lng": -1.144468,
  "wilaya_slug": "46-aïn-témouchent",
  "name_fr": null,
  "name_ar": "دار الثقافة عيسى مسعودي",
  "nid_fr": null,
  "nid_ar": "271"
 },
 {
  "layer": "cultural-directorate",
  "type_class": "various small embassy",
  "lat": 35.744518,
  "lng": 0.560046,
  "wilaya_slug": "48-relizane",
  "name_fr": null,
  "name_ar": "مديرية الثقافة",
  "nid_fr": null,
  "nid_ar": "1136"
 }
]